rust1/__init__.py
rust1/data
rust1/__main__.py
myrustdump1-1.82.0.dist-info/METADATA
myrustdump1-1.82.0.dist-info/WHEEL
myrustdump1-1.82.0.dist-info/RECORD
