Metadata-Version: 2.1
Name: myrustdump1
Version: 1.82.0
Summary: Rust is awsome
License: MIT
Classifier: License :: OSI Approved :: MIT License
Project-URL: Homepage, https://ziglang.org
Project-URL: Source Code, https://github.com/ziglang/zig-pypi
Project-URL: Bug Tracker, https://github.com/ziglang/zig-pypi/issues
Requires-Python: >=3.11
